cacheables/__init__.py
cacheables/caches/__init__.py
cacheables/caches/base.py
cacheables/caches/disk.py
cacheables/cli.py
cacheables/controllers.py
cacheables/core.py
cacheables/decorator.py
cacheables/exceptions.py
cacheables/keys.py
cacheables/logging.py
cacheables/metadata.py
cacheables/serializers/__init__.py
cacheables/serializers/base.py
cacheables/serializers/json_.py
cacheables/serializers/pickle_.py
cacheables-0.3.2.dist-info/METADATA
cacheables-0.3.2.dist-info/WHEEL
cacheables-0.3.2.dist-info/entry_points.txt
cacheables-0.3.2.dist-info/RECORD
