Metadata-Version: 2.1
Name: cacheables
Version: 0.3.2
Summary: 
Home-page: https://github.com/thomelane/cacheables
Author: Thom Lane
Author-email: thom.e.lane@gmail.com
Requires-Python: >=3.9,<4.0
Classifier: Programming Language :: Python :: 3
Classifier: Programming Language :: Python :: 3.9
Classifier: Programming Language :: Python :: 3.10
Classifier: Programming Language :: Python :: 3.11
Requires-Dist: click (>=8.1.6,<9.0.0)
Requires-Dist: loguru (>=0.7.0,<0.8.0)
Project-URL: Repository, https://github.com/thomelane/cacheables
